[
    {
        "plan_number": 1,
        "plan_subject": "Language Arts",
        "months": [
            {
                "month_name": "October",
                "topics": [
                    "**Reading Comprehension**",
                    "**Literary Elements**",
                    "**Vocabulary Development**"
                ],
                "summary": "In October, the student will focus on reading comprehension skills, exploring literary elements such as character, setting, and plot, along with enhancing their vocabulary. This foundational knowledge will prepare the student to analyze texts more deeply in later months."
            },
            {
                "month_name": "November",
                "topics": [
                    "**Text Structure**",
                    "**Theme and Main Idea**",
                    "**Context Clues**"
                ],
                "summary": "November will delve into text structures and how they affect understanding. The student will learn to identify themes and main ideas in texts, using context clues to improve comprehension. These skills are crucial for interpreting more complex readings and will boost critical thinking."
            },
            {
                "month_name": "December",
                "topics": [
                    "**Narrative Writing**",
                    "**Descriptive Language**",
                    "**Peer Review Techniques**"
                ],
                "summary": "In December, the focus will shift to narrative writing, emphasizing the use of descriptive language. The student will also learn peer review techniques, fostering analytical skills that will assist in improving their own writing. This month builds the foundation for personal expression in text."
            },
            {
                "month_name": "January",
                "topics": [
                    "**Argumentative Writing**",
                    "**Citing Evidence**",
                    "**Logical Fallacies**"
                ],
                "summary": "January introduces argumentative writing, focusing on how to cite evidence effectively and recognize logical fallacies. This month prepares the student for persuasive communication, an important skill in both academic settings and real-world interactions."
            },
            {
                "month_name": "February",
                "topics": [
                    "**Poetry Analysis**",
                    "**Figurative Language**",
                    "**Rhyme and Meter**"
                ],
                "summary": "February will be dedicated to poetry analysis, where the student will explore figurative language along with rhyme and meter. Learning how to analyze poetry enhances not only appreciation for the genre but also encourages creative expression."
            },
            {
                "month_name": "March",
                "topics": [
                    "**Research Skills**",
                    "**Summarizing Information**",
                    "**Writing Research Papers**"
                ],
                "summary": "In March, the student will acquire research skills, focusing on summarizing information and writing research papers. This knowledge is essential for future academic projects and improves the student\u2019s ability to engage with diverse sources."
            },
            {
                "month_name": "April",
                "topics": [
                    "**Oral Presentation Skills**",
                    "**Developing Arguments**",
                    "**Critical Listening**"
                ],
                "summary": "April emphasizes oral presentation skills, teaching students to develop coherent arguments and practice critical listening. These abilities will aid the student in articulating thoughts clearly, a valuable skill across all subjects and social situations."
            }
        ]
    }
]