[
    {
        "lessons": [
            {
                "title": "Unlocking Percentages: A Comprehensive Review",
                "lecture": "Hello! Today, we will consolidate your understanding of percentages through a series of exercises, including some challenge problems and real-life scenarios that need percentages. Let's start with a comprehensive review of percentages. \n\nPercentages are a way of expressing a number as a fraction out of 100. This is especially useful when you want to compare quantities in relation to a whole. For example, if you have 50 apples and 25 of those are red, you could express this as 25% of the apples are red. This means that if you know the total amount, you can easily calculate what portion of that amount is represented by the part. Remember, the formula to calculate percentage is:\n\nPercentage = (Part / Whole) \u00d7 100.  \n\nNow, let\u2019s practice some exercises to reinforce this concept. How about calculating percentages of your quiz scores from last week? If you scored 80 out of 100, what percentage is that? That's right, it\u2019s 80%! Now, practice with these numbers: What is 30% of 250? \n\nYou find that by calculating (30/100) \u00d7 250 which gives you 75. Keep practicing those calculations. Now, let's [p] move to challenge problems where we\u2019ll take it a step further. Try this: If there\u2019s a price increase of 20% on an item that costs $50, what is the new price? \n\nTo find that, you multiply $50 by 0.20, which gives you $10. Then, you add that $10 to the original $50, resulting in $60.  Keep these challenges in mind, as they apply to real-life shopping scenarios, where knowing percentages helps you decide on deals or discounts.\nLet\u2019s take a 5-minute break and then we will move into real-life application scenarios of percentages.\nWelcome back! Let\u2019s discuss real-life applications of percentages. Understanding percentages is incredibly valuable in financial literacy. Let\u2019s consider a real-world scenario: calculating your monthly expenses. If you notice that 30% of your earnings goes to rent, 20% on groceries, and 15% on utilities, it\u2019s crucial to understand how these percentages affect your budgeting.\n\nLet\u2019s set up a scenario: Suppose you earn 2000 a month. If your rent is 30%, how much do you pay? That\u2019s right, 30% of 2000 is 600. So, after rent, if you also allocate 400 for groceries (20%) and 300 for utilities (15%), you will have a clearer financial picture based on percentages.\n\nNow, let\u2019s apply what we have learned with some more exercise problems that combine challenge percentages and financial calculations. For instance, if you want to save 15% of your monthly salary, what would that amount be based on your earnings of 2000?\n\nBy now, I hope you see how vital percentages are in everyday situations. Let's try one last application: If an item originally costs 80 and is on sale at 25% off, how much do you end up spending?\nLet\u2019s calculate: first find what the discount amount is: 25% of 80 is 20. Therefore, your final price is 80 - 20, which equals 60.\n\nYou\u2019ve done a fantastic job today dealing with percentages, challenges, and real-life scenarios!\n\nLet\u2019s summarize today\u2019s lesson. We have discussed how to calculate percentages, worked through challenge problems, and applied percentages to real-life situations. Understanding percentages equips you with valuable skills for managing finances, shopping, and making informed decisions in various aspects of daily life. Keep practicing, and you'll continue to improve!\n\nThank you for your hard work today! Have any questions? Let's discuss. \nThe main topic was percentages, and the subtopics covered were: 1. Comprehensive review of percentages; 2. Challenge problems; 3. Real-life application scenarios.",
                "summary": "Today's lecture focused on consolidating your understanding of percentages through comprehensive exercises, challenge problems, and real-life applications. We explored how to calculate percentages, discussed their importance in financial literacy, and tackled problems related to budgeting and discounts.",
                "subject": "Mathematics",
                "main_topic": "Percentages",
                "sub_topics": [
                    "Comprehensive review of percentages",
                    "Challenge problems",
                    "Real-life application scenarios"
                ],
                "wikipedia_refrences": [
                    "https://en.wikipedia.org/wiki/Percentage",
                    "https://en.wikipedia.org/wiki/Ratio_%26_proportion"
                ],
                "quiz": [
                    {
                        "question": "What formula is used to calculate percentage?",
                        "options": [
                            "3) Percentage = (Part \u00d7 Whole) / 100",
                            "2) Percentage = (Whole / Part) \u00d7 100",
                            "1) Percentage = (Part / Whole) \u00d7 100",
                            "4) Percentage = (Whole + Part) \u00d7 100"
                        ],
                        "explanation": "The correct formula to calculate percentage is to divide the part by the whole and then multiply by 100.",
                        "answer": "1) Percentage = (Part / Whole) \u00d7 100"
                    },
                    {
                        "question": "If you scored 80 out of 100 on a quiz, what percentage did you achieve?",
                        "options": [
                            "3) 60%",
                            "1) 80%",
                            "2) 70%",
                            "4) 75%"
                        ],
                        "explanation": "To find the percentage, use the formula: (80/100) \u00d7 100 = 80%.",
                        "answer": "1) 80%"
                    },
                    {
                        "question": "What is 30% of 250?",
                        "options": [
                            "4) 60",
                            "1) 75",
                            "2) 70",
                            "3) 80"
                        ],
                        "explanation": "To calculate 30% of 250, (30/100) \u00d7 250 = 75.",
                        "answer": "1) 75"
                    },
                    {
                        "question": "If an item costs $50 and there is a 20% price increase, what is the new price?",
                        "options": [
                            "4) $50",
                            "2) $70",
                            "1) $60",
                            "3) $55"
                        ],
                        "explanation": "A 20% increase on $50 means you add $10 to the original price (20% of $50 is $10), resulting in $60.",
                        "answer": "1) $60"
                    },
                    {
                        "question": "If you earn $2000 a month and spend 30% on rent, how much do you pay for rent?",
                        "options": [
                            "4) $800",
                            "2) $500",
                            "1) $600",
                            "3) $700"
                        ],
                        "explanation": "30% of $2000 is calculated as (30/100) \u00d7 2000 = $600 for rent.",
                        "answer": "1) $600"
                    },
                    {
                        "question": "What is the final price of a $80 item with a 25% discount?",
                        "options": [
                            "1) $60",
                            "3) $70",
                            "2) $55",
                            "4) $65"
                        ],
                        "explanation": "The discount amount is 25% of $80, which is $20. Subtracting this from $80 gives a final price of $60.",
                        "answer": "1) $60"
                    },
                    {
                        "question": "If you have 40 apples and 10 of them are green, what percentage of the apples are green?",
                        "options": [
                            "1) 25%",
                            "4) 15%",
                            "2) 30%",
                            "3) 20%"
                        ],
                        "explanation": "10 out of 40 apples means (10/40) \u00d7 100 = 25%.",
                        "answer": "1) 25%"
                    },
                    {
                        "question": "If your monthly salary is $3000 and you allocate 10% for savings, how much will you save?",
                        "options": [
                            "3) $200",
                            "4) $350",
                            "2) $400",
                            "1) $300"
                        ],
                        "explanation": "10% of $3000 is calculated as (10/100) \u00d7 3000 = $300 in savings.",
                        "answer": "1) $300"
                    },
                    {
                        "question": "A car originally priced at $20000 is on a 15% discount. What is the discount amount?",
                        "options": [
                            "1) $3000",
                            "3) $3500",
                            "2) $2500",
                            "4) $4000"
                        ],
                        "explanation": "The discount amount from the original price is calculated as (15/100) \u00d7 20000 = $3000.",
                        "answer": "1) $3000"
                    },
                    {
                        "question": "If a test has 12 questions and you answered 9 correctly, what percentage did you get correct on the test?",
                        "options": [
                            "1) 75%",
                            "4) 70%",
                            "3) 60%",
                            "2) 80%"
                        ],
                        "explanation": "The percentage correct is calculated as (9/12) \u00d7 100, which equals 75%.",
                        "answer": "1) 75%"
                    }
                ],
                "lecture_questions": [
                    {
                        "question": "If you scored 45 out of 60 on your exam, what percentage did you achieve?",
                        "options": [
                            "4) 90%",
                            "1) 75%",
                            "3) 85%",
                            "2) 80%"
                        ],
                        "explanation": "To calculate the percentage, you can use the formula: Percentage = (Part / Whole) \u00d7 100. Here, Part = 45 and Whole = 60. So, (45/60) \u00d7 100 = 75%. Therefore, the correct answer is 75%.",
                        "answer": "1) 75%"
                    },
                    {
                        "question": "If you earn $2000 per month and you want to save 15% of your earnings, how much will you save?",
                        "options": [
                            "2) $300",
                            "1) $200",
                            "4) $600",
                            "3) $400"
                        ],
                        "explanation": "To find 15% of $2000, you multiply $2000 by 0.15, which equals $300. Therefore, you would save $300.",
                        "answer": "2) $300"
                    }
                ]
            }
        ],
        "complete": true
    }
]