[
    {
        "lessons": [
            {
                "title": "Understanding Algebraic Expressions",
                "lecture": "Today, we will begin learning about algebraic expressions. This includes understanding what they are and how they are formed. Algebraic expressions are combinations of numbers, variables, and operations. They can represent mathematical relationships and are fundamental to all areas of mathematics. Understanding the components of algebraic expressions will empower you to work with them more effectively in various equations and problems. Let's dive deeper into three key components of algebraic expressions: variables, coefficients, and constant terms. [p]\n\nFirst, let's talk about variables. A variable is a symbol, typically a letter, that represents an unknown value or quantity. For example, in the expression 2x + 5, 'x' is the variable. Variables allow us to generalize mathematical statements and work with them without needing specific numbers. Essentially, they serve as placeholders for values that may change. Knowing that variables can take on different values is crucial as we work through algebraic equations and functions. [p] You can think of variables as the building blocks of algebraic expressions.\n\nNext, we have coefficients. A coefficient is a number that multiplies a variable. In the expression 3y, the number 3 is the coefficient of the variable y. Coefficients tell us how many times we are adding or multiplying the variable in question. They can be positive or negative, and if a variable doesn't have a coefficient explicitly written, it is understood to be 1. For instance, in the expression z, the coefficient is 1, meaning 1z or just z. Coefficients play a key role in determining the value of an expression as they directly affect the outcome when the variable is substituted with numerical values. [p]\n\nNow, moving on to constant terms. A constant term is a number on its own in an expression, without any variables attached. For example, in the expression 4x + 7, the number 7 is the constant term. Constants serve as fixed values that do not change and provide a base number in an algebraic expression. Understanding constant terms is essential because they help us determine the final value of an expression when the variables are given specific values. They also help us understand the behavior of functions and equations when graphed. [p]\n\nCombining these components forms algebraic expressions that can be manipulated through various mathematical operations. For instance, take a look at the expression 4x + 3y - 5z + 10. Here, 4, 3, and -5 are coefficients, x, y, and z are variables, and 10 serves as the constant term. By identifying and separating these components, you will have a better understanding of how to simplify, expand, or evaluate algebraic expressions based on the values given for the variables involved. [p]\n\nNow, let\u2019s look at how to simplify an algebraic expression. Simplifying means rewriting the expression to its most basic form while maintaining its equivalence. This can be done by combining like terms\u2014terms that have the same variable raised to the same power. For example, in the expression 2x + 3x - 5y + 4y, you can combine the like terms as follows: (2x + 3x) becomes 5x and (-5y + 4y) becomes -y. So, the simplified form of the original expression is 5x - y. Understanding how to simplify expressions is crucial as it leads to easier calculations and clearer representations of mathematical relationships. [p]\n\nNext, we should consider the significance of algebraic expressions in solving equations. An equation is a statement that two expressions are equal, and algebraic expressions are utilized to formulate these statements. For example, if you have the equation 3x + 2 = 11, you are using the algebraic expression 3x + 2 in order to solve for the unknown variable x. There is a systematic approach to isolate the variable and determine its value. This practice is foundational for more advanced mathematics. [p]\n\nTo further illustrate the application of algebraic expressions, let\u2019s discuss functions. A function relates an input to an output and is often represented as an equation or expression. For example, consider the function f(x) = 2x + 3. In this case, the input x will determine the output by following the expression. Functions can be graphed, allowing us to visually interpret the relationship between variables. Learning how to manipulate algebraic expressions plays a critical role in comprehending and working with functions. [p]\n\nIn summary, today we covered a variety of foundational concepts regarding algebraic expressions. You learned what algebraic expressions are and their significance in mathematics. We explored the three key components: variables, coefficients, and constant terms. Additionally, we discussed the process of simplifying expressions and how they are utilized in solving equations and functions. The understanding of these concepts is vital as you progress in your math education. [p]  Now let's consolidate what you have learned today by stating the main topic and subtopics clearly. The main topic was Algebraic Expressions and the subtopics we covered include Variables, Coefficients, and Constant Terms. Understanding these components will serve as a strong foundation for your continued algebra studies. [p]",
                "summary": "In today's lecture, you learned about algebraic expressions, focusing on their components, which include variables, coefficients, and constant terms. You also explored the process of simplifying expressions and how they are integral in solving equations and functions. This foundational knowledge will be critical as you move forward in your studies of algebra and mathematics in general.",
                "subject": "Mathematics",
                "main_topic": "Algebraic Expressions",
                "sub_topics": [
                    "Variables",
                    "Coefficients",
                    "Constant Terms"
                ],
                "wikipedia_refrences": [
                    "https://en.wikipedia.org/wiki/Variable",
                    "https://en.wikipedia.org/wiki/Coefficient",
                    "https://en.wikipedia.org/wiki/Constant_term"
                ],
                "quiz": [
                    {
                        "question": "What is the role of a variable in an algebraic expression?",
                        "options": [
                            "2) It indicates a number that multiplies another number.",
                            "3) It serves as a symbol for an unknown value.",
                            "4) It is a constant term.",
                            "1) It represents a fixed value."
                        ],
                        "explanation": "A variable is a symbol, typically a letter, that represents an unknown value or quantity, serving as a placeholder for values that may change.",
                        "answer": "3) It serves as a symbol for an unknown value."
                    },
                    {
                        "question": "Which of the following statements is true about coefficients?",
                        "options": [
                            "3) Coefficients indicate how many times we are multiplying a variable.",
                            "2) If a variable has no coefficient written, it is understood to be 0.",
                            "4) Coefficients always have to be numbers other than 1.",
                            "1) Coefficients can only be positive."
                        ],
                        "explanation": "Coefficients tell us how many times we are adding or multiplying the variable in question, and if a variable has no coefficient explicitly written, it is understood to be 1.",
                        "answer": "3) Coefficients indicate how many times we are multiplying a variable."
                    },
                    {
                        "question": "In the expression 5x - 8, what is the constant term?",
                        "options": [
                            "1) 5",
                            "3) -8",
                            "2) x",
                            "4) -5"
                        ],
                        "explanation": "The constant term is a number on its own in an expression without any variables attached, which in this case is -8.",
                        "answer": "3) -8"
                    },
                    {
                        "question": "How are like terms combined in the expression 6a + 9a - 4?",
                        "options": [
                            "1) 15a - 4",
                            "4) 3a + 4",
                            "3) 3a - 4",
                            "2) 15a + 4"
                        ],
                        "explanation": "Combining like terms 6a + 9a gives 15a, and -4 remains the same, so the simplified expression is 15a - 4.",
                        "answer": "1) 15a - 4"
                    },
                    {
                        "question": "Which mathematical operation is essential for simplifying expressions?",
                        "options": [
                            "1) Subtraction of all terms.",
                            "2) Division of constants only.",
                            "4) Finding the average of coefficients.",
                            "3) Combining like terms."
                        ],
                        "explanation": "Simplifying an expression involves rewriting it to its most basic form, which is achieved by combining like terms\u2014terms that have the same variable raised to the same power.",
                        "answer": "3) Combining like terms."
                    },
                    {
                        "question": "What does the expression 4x + 3y - 5z + 10 indicate about its components?",
                        "options": [
                            "2) 10 is a variable.",
                            "3) 4, 3, and -5 are coefficients, x, y, and z are variables, and 10 is a constant.",
                            "4) All terms are variables.",
                            "1) 4, 3, and -5 are constants."
                        ],
                        "explanation": "In the expression 4x + 3y - 5z + 10, the numbers 4, 3, and -5 are coefficients, while x, y, and z are variables, making 10 the constant term.",
                        "answer": "3) 4, 3, and -5 are coefficients, x, y, and z are variables, and 10 is a constant."
                    },
                    {
                        "question": "Which of the following expressions is not an algebraic expression?",
                        "options": [
                            "2) 5x\u00b2 + 7",
                            "1) 3a + 4b - 2",
                            "4) 7xy/z",
                            "3) 10 - 3"
                        ],
                        "explanation": "Generally, algebraic expressions combine variables and constants with operations, but not equations that indicate equality, like '2 = 3'. Here all options are algebraic except one that is an equation represented improperly.",
                        "answer": "3). All are algebraic expressions."
                    },
                    {
                        "question": "What do we call an equation that uses an algebraic expression to represent a relationship between variables?",
                        "options": [
                            "1) A variable expression.",
                            "4) A function.",
                            "2) An inequality.",
                            "3) A linear equation."
                        ],
                        "explanation": "An equation that states that two expressions are equal typically represents a relationship between variables through algebraic expressions, making it a linear equation if it is in the form of a linear expression.",
                        "answer": "3) A linear equation."
                    },
                    {
                        "question": "What is the relationship between an input and output in a function represented by an algebraic expression?",
                        "options": [
                            "1) Input is constant and does not change.",
                            "3) Input determines the output according to a specific rule or expression.",
                            "4) There is no relationship.",
                            "2) Output is always larger than the input."
                        ],
                        "explanation": "A function relates an input to an output, and the expression used defines how the input will determine the output value through a specific mathematical relationship.",
                        "answer": "3) Input determines the output according to a specific rule or expression."
                    },
                    {
                        "question": "In the expression 2y + 4 - y, how would you simplify it?",
                        "options": [
                            "3) y + 2",
                            "1) y + 4",
                            "4) 6y + 4",
                            "2) 2y - 4"
                        ],
                        "explanation": "By combining like terms, 2y - y yields y, and the constant 4 remains the same, so the simplified expression is y + 4.",
                        "answer": "1) y + 4."
                    }
                ],
                "lecture_questions": [
                    {
                        "question": "What are the three key components of algebraic expressions?",
                        "options": [
                            "3) Numbers, operations, outcomes",
                            "4) Terms, factors, multiples",
                            "1) Variables, coefficients, constant terms",
                            "2) Variables, equations, functions"
                        ],
                        "explanation": "The three key components of algebraic expressions include variables (symbols that represent unknown values), coefficients (numerical factors in front of variables), and constant terms (numbers on their own). This understanding is crucial for working with algebraic expressions effectively.",
                        "answer": "1) Variables, coefficients, constant terms"
                    },
                    {
                        "question": "What does a variable represent in an algebraic expression?",
                        "options": [
                            "1) A specific number",
                            "2) An unknown value or quantity",
                            "4) A constant value",
                            "3) A mathematical operation"
                        ],
                        "explanation": "A variable is a symbol that represents an unknown value or quantity. This allows for generalization in mathematical expressions, enabling manipulation without needing specific numbers.",
                        "answer": "2) An unknown value or quantity"
                    },
                    {
                        "question": "What is the coefficient in the expression 5x?",
                        "options": [
                            "1) 5",
                            "3) 1",
                            "2) x",
                            "4) 0"
                        ],
                        "explanation": "In the expression 5x, the number 5 is the coefficient that multiplies the variable x. It indicates how many times the variable x is being considered or counted. Thus, the correct answer is 5.",
                        "answer": "1) 5"
                    },
                    {
                        "question": "In the expression 4x + 7, what is the constant term?",
                        "options": [
                            "2) 7",
                            "4) 0",
                            "1) 4",
                            "3) x"
                        ],
                        "explanation": "The constant term in an expression is the number without any variable attached. In the expression 4x + 7, the number 7 is the constant term because it stands alone without any variables.",
                        "answer": "2) 7"
                    },
                    {
                        "question": "In the expression 4x + 3y - 5z + 10, what is the coefficient of y?",
                        "options": [
                            "4) 10",
                            "2) 3",
                            "3) -5",
                            "1) 4"
                        ],
                        "explanation": "The coefficient of a variable in an algebraic expression is the numerical factor that is multiplied by the variable. In the expression 4x + 3y - 5z + 10, the term 3y indicates that 3 is the coefficient of y.",
                        "answer": "2) 3"
                    },
                    {
                        "question": "What is the simplified form of the expression 2x + 3x - 5y + 4y?",
                        "options": [
                            "3) 1x + 1y",
                            "2) 5x - y",
                            "4) 0",
                            "1) 5x + y"
                        ],
                        "explanation": "To simplify the expression 2x + 3x - 5y + 4y, combine like terms. 2x + 3x equals 5x and -5y + 4y equals -y. Therefore, the correct simplified form is 5x - y.",
                        "answer": "2) 5x - y"
                    },
                    {
                        "question": "What is the purpose of algebraic expressions in the context of solving equations?",
                        "options": [
                            "4) To provide numerical values for calculation purposes",
                            "2) To formulate statements that define the equality of two expressions",
                            "1) To create a visual representation of numbers",
                            "3) To find the geometric area of shapes"
                        ],
                        "explanation": "Algebraic expressions are essential in expressing mathematical relationships. They enable us to formulate equations that represent equality between two expressions, which is critical for solving for unknown variables such as x in the equation 3x + 2 = 11.",
                        "answer": "2) To formulate statements that define the equality of two expressions"
                    },
                    {
                        "question": "What does the function f(x) = 2x + 3 represent in mathematical terms?",
                        "options": [
                            "2) A constant function with no variables",
                            "1) A relation between a single input and a single output",
                            "4) An equation with multiple inputs and outputs",
                            "3) A representation of a quadratic equation"
                        ],
                        "explanation": "The function f(x) = 2x + 3 represents a linear relationship where each input value of x corresponds to exactly one output value calculated by the expression. This function illustrates a relation between a specific input (x) and a specific output (f(x)).",
                        "answer": "1) A relation between a single input and a single output"
                    },
                    {
                        "question": "What are the three key components of algebraic expressions?",
                        "options": [
                            "1) Variables, constants, and functions",
                            "2) Coefficients, exponents, and roots",
                            "3) Variables, coefficients, and constant terms",
                            "4) Factors, multiples, and integers"
                        ],
                        "explanation": "The three key components of algebraic expressions include variables (which represent quantities that can change), coefficients (which are numerical factors associated with variables), and constant terms (which are fixed values). Understanding these components is essential for working with algebraic expressions effectively.",
                        "answer": "3) Variables, coefficients, and constant terms"
                    },
                    {
                        "question": "Which of the following correctly defines a coefficient in an algebraic expression?",
                        "options": [
                            "4) The result of adding or subtracting terms.",
                            "2) A number that is multiplied by a variable.",
                            "1) A letter or symbol that represents a number.",
                            "3) A term that has no variable associated with it."
                        ],
                        "explanation": "A coefficient is specifically the numerical factor that is multiplied by a variable in an expression. For example, in the expression 5x, '5' is the coefficient of the variable 'x'.",
                        "answer": "2) A number that is multiplied by a variable."
                    },
                    {
                        "question": "What is the primary function of the cell membrane?",
                        "options": [
                            "1) To store genetic information",
                            "4) To facilitate cell division",
                            "2) To regulate the movement of substances in and out of the cell",
                            "3) To provide energy for cellular processes"
                        ],
                        "explanation": "The primary function of the cell membrane is to regulate what enters and exits the cell, thus maintaining homeostasis. It acts as a protective barrier and is selective about what substances can pass through.",
                        "answer": "2) To regulate the movement of substances in and out of the cell"
                    }
                ]
            }
        ],
        "complete": true
    }
]